md2tree/__init__.py
md2tree/_md2tree.py
md2tree/parse.py
md2tree/utils.py
md2tree-0.1.0.dist-info/LICENSE
md2tree-0.1.0.dist-info/METADATA
md2tree-0.1.0.dist-info/WHEEL
md2tree-0.1.0.dist-info/RECORD
