Metadata-Version: 2.3
Name: md2tree
Version: 0.1.0
Summary: 
License: Apach-2.0
Author: Kohei Watanabe
Author-email: koheitech001@gmail.com
Requires-Python: >=3.10,<3.14
Classifier: License :: Other/Proprietary License
Classifier: Programming Language :: Python :: 3
Classifier: Programming Language :: Python :: 3.10
Classifier: Programming Language :: Python :: 3.11
Classifier: Programming Language :: Python :: 3.12
Classifier: Programming Language :: Python :: 3.13
Requires-Dist: pyproject-toml (>=0.1.0,<0.2.0)
Requires-Dist: treelib (>=1.6.4,<2.0.0)
